Workbook

Sheet 汇总
A1: 景气与磨具需求 汇总看板
A2: 改这里没用，数值全部来自「评分卡」和「磨具代理」。
A4: 瓷砖行业景气分 | B4: =评分卡!I17
A5: 景气分级 | B5: =IF(评分卡!I17>0.5,"景气上行",IF(评分卡!I17<-0.5,"景气下行","中性震荡"))
A7: 磨边/抛光耗材 代理分 | B7: ='磨具代理'!E13
A8: 压机模具 代理分 | B8: ='磨具代理'!E14
A10: 判读规则
A11: · 景气分 > 0.5 且耗材代理分 > 0：耗材需求向上，重点看产量能否持续
A12: · 景气分 < -0.5 且压机模具分 < 0：扩产停滞，模具端承压更早更久
A13: · 景气分与耗材分背离：多半是出口或结构在抵消国内产量下滑，去查明细
A14: · 两个磨具分背离：说明「产量」与「资本开支」周期错位，属正常，要分开表述

Sheet 原始数据
A1: 原始数据登记表（一行一个数据点，只增不改）
A3: 日期 | B3: 指标 | C3: 值 | D3: 单位 | E3: 来源 | F3: 链接 | G3: 备注
A4: 2026-09-30 | B4: 地产竣工面积同比 | C4: -12.5 | D4: % | E4: 国家统计局 | G4: 示例行，请替换为真实数据
A5: 2026-09-30 | B5: 瓷砖产量同比 | C5: -8 | D5: % | E5: 示例来源 | G5: 示例行，请替换为真实数据

Sheet 评分卡
A1: 景气评分卡（得分列手工填 -2 ~ +2，其余自动算）
A2: 负向指标已标注方向=负，请直接填带符号的分数（例如库存天数上升 => 填 -1）。
A4: 类别 | B4: 指标 | C4: 方向 | D4: 权重 | E4: 最新值 | F4: 上期值 | G4: 同比/变化 | H4: 得分 | I4: 加权分 | J4: 打分依据（必填） | K4: 数据日期
A5: 需求 | B5: 地产竣工面积同比 | C5: 正 | D5: 0.15 | E5: -25.1 | F5: -23.7 | G5: =IFERROR((E5-F5)/ABS(F5),"") | H5: -1 | I5: =IF(H5="","",D5*H5) | J5: 变化 -1.40pp，温和恶化 | K5: 46295
A6: 需求 | B6: 商品房销售面积同比 | C6: 正 | D6: 0.05 | E6: -13.2 | F6: -12.1 | G6: =IFERROR((E6-F6)/ABS(F6),"") | H6: -1 | I6: =IF(H6="","",D6*H6) | J6: 变化 -1.10pp，温和恶化 | K6: 46295
A7: 需求 | B7: 瓷砖产量同比 | C7: 正 | D7: 0.15 | E7: -15.07 | F7: -12.87 | G7: =IFERROR((E7-F7)/ABS(F7),"") | H7: -2 | I7: =IF(H7="","",D7*H7) | J7: 变化 -2.20pp，显著恶化 | K7: 46203
A8: 需求 | B8: 瓷砖出口金额同比 | C8: 正 | D8: 0.1 | E8: -4.32 | G8: =IFERROR((E8-F8)/ABS(F8),"") | H8: 1 | I8: =IF(H8="","",D8*H8) | J8: 8月单月出口额同比 -4.32%，明显好于 1—8月累计的 -7.72%，降幅收窄即边际改善；因缺 7 月单月值无法算严格变化，按定性 +1 处理（人工判断 2026-10-27）
A9: 供给 | B9: 行业开工率 | C9: 正 | D9: 0.05 | E9: 2 | G9: =IFERROR((E9-F9)/ABS(F9),"") | H9: -2 | I9: =IF(H9="","",D9*H9) | J9: 定性档位 2/2（历史低位）：江西高安约7成、上高宜丰8-9成，但国内其它产区普遍不足50%，行业开窑率处于历史低位（人工判断 2026-10-27）
A10: 供给 | B10: 库存天数 | C10: 负 | D10: 0.05 | E10: 136.91 | F10: 129.84 | G10: =IFERROR((E10-F10)/ABS(F10),"") | H10: -2 | I10: =IF(H10="","",D10*H10) | J10: 变化 +7.07pp，显著恶化 | K10: 46203
A11: 价格 | B11: 瓷砖价格指数 | C11: 正 | D11: 0.1 | E11: 1 | G11: =IFERROR((E11-F11)/ABS(F11),"") | H11: 1 | I11: =IF(H11="","",D11*H11) | J11: 无公开价格指数，按「定性档位法」：1档（涨价函广但落地存疑）→ +1。依据：8.29-9.5 七产区集中涨价函，但属煤价成本推动且终端难落地（人工判断 2026-10-27）
A12: 成本 | B12: 能源成本（天然气） | C12: 负 | D12: 0.05 | E12: 6749.4 | F12: 6185.9 | G12: =IFERROR((E12-F12)/ABS(F12),"") | H12: -2 | I12: =IF(H12="","",D12*H12) | J12: 变化 +563.50pp，显著恶化 | K12: 46315
A13: 盈利 | B13: 上市公司毛利率 | C13: 正 | D13: 0.1 | E13: 26.16 | F13: 25.66 | G13: =IFERROR((E13-F13)/ABS(F13),"") | H13: 1 | I13: =IF(H13="","",D13*H13) | J13: 变化 +0.50pp，温和改善 | K13: 46203
A14: 信用 | B14: 应收账款周转天数 | C14: 负 | D14: 0.05 | E14: 58.39 | F14: 73.97 | G14: =IFERROR((E14-F14)/ABS(F14),"") | H14: 1 | I14: =IF(H14="","",D14*H14) | J14: 天数 73.97→58.39 降 15.6 天，但同期营收同比 -15.1%，分母缩水效应显著，不能直接视为回款改善，由 +2 下调至 +1（人工判断 2026-10-27） | K14: 46203
A15: 政策 | B15: 地产政策强度 | C15: 正 | D15: 0.1 | E15: 3 | G15: =IFERROR((E15-F15)/ABS(F15),"") | H15: 2 | I15: =IF(H15="","",D15*H15) | J15: 水平型指标，不适用变化法。Q3 政策强度 3/3 分（8·28全国性文件+一线放松），按「3分→+2」映射（人工判断 2026-10-27）
A16: 政策 | B16: 环保/能耗政策 | C16: 负 | D16: 0.05 | E16: 1 | G16: =IFERROR((E16-F16)/ABS(F16),"") | H16: -1 | I16: =IF(H16="","",D16*H16) | J16: 负向指标，定性档位 1/2：建筑卫生陶瓷纳入2026年度工业节能监察重点，多地环保管控叠加订单不足致停窑减产，但未见主产区大范围停限产（人工判断 2026-10-27）
B17: 景气分（加权合计） | I17: =SUM(I5:I16) | J17: ← 结果在「汇总」Sheet
B19: 未填得分的指标按 0 计，会稀释景气分 —— 数据缺失时请在依据列写明「缺数据，按 0 处理」。

Sheet 磨具代理
A1: 磨具需求代理分（两个分分开算，不要混）
A2: 得分列自动引用「评分卡」对应指标；标记「手工」的行请自己填 -2 ~ +2。
A4: 归属 | B4: 驱动因素 | C4: 映射权重 | D4: 得分 | E4: 加权分 | F4: 说明
A5: 磨边/抛光耗材 | B5: 瓷砖产量同比 | C5: 0.4 | D5: =评分卡!H7 | E5: =IF(D5="","",C5*D5) | F5: 同步，权重最高
A6: 磨边/抛光耗材 | B6: 行业开工率 | C6: 0.25 | D6: =评分卡!H9 | E6: =IF(D6="","",C6*D6) | F6: 消耗强度
A7: 磨边/抛光耗材 | B7: 大规格/岩板占比 | C7: 0.2 | E7: =IF(D7="","",C7*D7) | F7: 手工：结构升级打分，缺数据按 0
A8: 磨边/抛光耗材 | B8: 瓷砖出口金额同比 | C8: 0.15 | D8: =评分卡!H8 | E8: =IF(D8="","",C8*D8) | F8: 间接
A9: 压机模具 | B9: 瓷砖企业资本开支 | C9: 0.55 | E9: =IF(D9="","",C9*D9) | F9: 手工：从财报/公告判断增减，缺数据按 0
A10: 压机模具 | B10: 新增产线 / 技改 | C10: 0.3 | E10: =IF(D10="","",C10*D10) | F10: 手工：从公告/新闻数项目
A11: 压机模具 | B11: 上市公司毛利率 | C11: 0.15 | D11: =评分卡!H13 | E11: =IF(D11="","",C11*D11) | F11: 盈利支撑扩产意愿
B13: 磨边/抛光耗材 代理分 | E13: =SUMIF(A5:A11,"磨边/抛光耗材",E5:E11)
B14: 压机模具 代理分 | E14: =SUMIF(A5:A11,"压机模具",E5:E11)
